sist1
