Metadata-Version: 1.1
Name: sist1
Version: 1.0.1
Summary: 兰楠在深圳标准技术研究部的工作
Home-page: https://user.qzone.qq.com/865377886
Author: lannan
Author-email: 865377886@qq.com
License: nan
Platform: UNKNOWN
Classifier: Environment :: Web Environment
Classifier: Intended Audience :: Developers
Classifier: Operating System :: OS Independent
Classifier: Topic :: Text Processing :: Indexing
Classifier: Topic :: Utilities
Classifier: Topic :: Internet
Classifier: Topic :: Software Development :: Libraries :: Python Modules
Classifier: Programming Language :: Python
Classifier: Programming Language :: Python :: 3
